cap_anndata/__init__.py
cap_anndata/backed_df.py
cap_anndata/backed_dict.py
cap_anndata/cap_anndata.py
cap_anndata/reader.py
cap_anndata-0.5.0.dist-info/licenses/LICENSE
cap_anndata-0.5.0.dist-info/METADATA
cap_anndata-0.5.0.dist-info/WHEEL
cap_anndata-0.5.0.dist-info/top_level.txt
cap_anndata-0.5.0.dist-info/RECORD
