Metadata-Version: 2.4
Name: cap_anndata
Version: 0.5.0
Summary: Partial read/write of AnnData (h5ad) files for low-memory operations with large datasets.
Home-page: https://github.com/cellannotation/cap-anndata
Author: R. Mukhin, A. Isaev
Author-email: roman@ebookapplications.com
Project-URL: Bug Tracker, https://github.com/cellannotation/cap-anndata/issues
Project-URL: Changelog, https://github.com/cellannotation/cap-anndata/blob/main/CHANGELOG.md
Project-URL: Documentation, https://github.com/cellannotation/cap-anndata/blob/main/HOWTO.md
Classifier: Programming Language :: Python :: 3.9
Classifier: License :: OSI Approved :: BSD License
Classifier: Operating System :: OS Independent
Requires-Python: >=3.9
License-File: LICENSE
Requires-Dist: numpy>=1.23.5
Requires-Dist: pandas>=2.2.0
Requires-Dist: anndata>=0.10.0
Provides-Extra: dev
Requires-Dist: pytest>=8.0.0; extra == "dev"
Requires-Dist: setuptools~=69.1.1; extra == "dev"
Dynamic: author
Dynamic: author-email
Dynamic: classifier
Dynamic: description
Dynamic: description-content-type
Dynamic: home-page
Dynamic: license-file
Dynamic: project-url
Dynamic: provides-extra
Dynamic: requires-dist
Dynamic: requires-python
Dynamic: summary
